[
    {
        "Title": "Movie1",
        "Actor": "Actor McActorson",
        "Director":{
            "Name": "Mr. Director",
            "Bio": "He is a director.  He's human.  He also directs.",
            "Birth Year": 1999,
            "Death Year": 2099
        },
        "Genre": {
            "Name": "Thriller",
            "Description": "Thriller is a scary movie."
        },
        "Released": "Today",
        "Image": ""
    },
    {
        "Title": "Movie2",
        "Actor": "Actor VanActorson",
        "Director":{
            "Name": "Mr. Director",
            "Bio": "He is a director.  He's human.  He also directs.",
            "Birth Year": 1999,
            "Death Year": 2099
        },
        "Genre": {
            "Name": "Thriller",
            "Description": "Thriller is a scary movie."
        },
        "Released": "Today",
        "Image": ""
    },
    {
        "Title": "Movie3",
        "Actor": "Actor St. Actorson",
        "Director":{
            "Name": "Mr. Director",
            "Bio": "He is a director.  He's human.  He also directs.",
            "Birth Year": 1999,
            "Death Year": 2099
        },
        "Genre": {
            "Name": "Thriller",
            "Description": "Thriller is a scary movie."
        },
        "Released": "Today",
        "Image": ""
    },
    {
        "Title": "Movie4",
        "Actor": "Actor A. Actorson",
        "Director":{
            "Name": "Mr. Director",
            "Bio": "He is a director.  He's human.  He also directs.",
            "Birth Year": 1999,
            "Death Year": 2099
        },
        "Genre": {
            "Name": "Thriller",
            "Description": "Thriller is a scary movie."
        },
        "Released": "Today",
        "Image": ""
    },
    {
        "Title": "Movie5",
        "Actor": "Actor B. Actorson",
        "Director":{
            "Name": "Mr. Director",
            "Bio": "He is a director.  He's human.  He also directs.",
            "Birth Year": 1999,
            "Death Year": 2099
        },
        "Genre": {
            "Name": "Thriller",
            "Description": "Thriller is a scary movie."
        },
        "Released": "Today",
        "Image": ""
    },
    {
        "Title": "Movie6",
        "Actor": "Actor T Actorson",
        "Director":{
            "Name": "Mr. Director",
            "Bio": "He is a director.  He's human.  He also directs.",
            "Birth Year": 1999,
            "Death Year": 2099
        },
        "Genre": {
            "Name": "Thriller",
            "Description": "Thriller is a scary movie."
        },
        "Released": "Today",
        "Image": ""
    },
    {
        "Title": "Movie7",
        "Actor": "Actor Actorski",
        "Director":{
            "Name": "Mr. Director",
            "Bio": "He is a director.  He's human.  He also directs.",
            "Birth Year": 1999,
            "Death Year": 2099
        },
        "Genre": {
            "Name": "Thriller",
            "Description": "Thriller is a scary movie."
        },
        "Released": "Today",
        "Image": ""
    },
    {
        "Title": "Movie8",
        "Actor": "Actor Actorville",
        "Director":{
            "Name": "Mr. Director",
            "Bio": "He is a director.  He's human.  He also directs.",
            "Birth Year": 1999,
            "Death Year": 2099
        },
        "Genre": {
            "Name": "Thriller",
            "Description": "Thriller is a scary movie."
        },
        "Released": "Today",
        "Image": ""
    },                        
    {
        "Title": "Movie9",
        "Actor": "Acter McActorson",
        "Director":{
            "Name": "Mr. Director",
            "Bio": "He is a director.  He's human.  He also directs.",
            "Birth Year": 1999,
            "Death Year": 2099
        },
        "Genre": {
            "Name": "Thriller",
            "Description": "Thriller is a scary movie."
        },
        "Released": "Today",
        "Image": ""
    },
    {
        "Title": "Movie10",
        "Actor": "Actur McActorson",
        "Director":{
            "Name": "Mr. Director",
            "Bio": "He is a director.  He's human.  He also directs.",
            "Birth Year": 1999,
            "Death Year": 2099
        },
        "Genre": {
            "Name": "Thriller",
            "Description": "Thriller is a scary movie."
        },
        "Released": "Today",
        "Image": ""
    }

]